<!DOCTYPE hibernate-mapping PUBLIC
	"-//Hibernate/Hibernate Mapping DTD 3.0//EN"
	"http://hibernate.sourceforge.net/hibernate-mapping-3.0.dtd"> 

<!-- This file has been generated by Salto-db Generator v1.0.16 / Hibernate pojos and xml mapping files. at Fri Jan 30 09:30:05 GMT-03:00 2009 -->
<hibernate-mapping package="br.edu.les.easyCorrection.pojo.sistema">
	<class name="EquipeHasUsuarioHasRoteiro" table="equipe_has_usuario_has_roteiro">

		<composite-id name="id" class="br.edu.les.easyCorrection.pojo.sistema.ChaveCompostaTernariaInteger" access="property" >  
          	<key-property name="key1" column="equipe_id" />
          	<key-property name="key2" column="usuario_id" />  
        	<key-property name="key3" column="roteiro_id" />
     	</composite-id> 

		
		<many-to-one name="equipe"	class="br.edu.les.easyCorrection.pojo.sistema.Equipe" column="equipe_id" cascade = "none" insert="false" update="false"/>
		<many-to-one name="roteiro"	class="br.edu.les.easyCorrection.pojo.roteiros.Roteiro" column="roteiro_id" cascade = "none" insert="false" update="false"/>
		<many-to-one name="usuario"	class="br.edu.les.easyCorrection.pojo.acesso.Usuario" column="usuario_id" cascade = "none" insert="false" update="false"/>
		
	</class>
</hibernate-mapping>